clfits/__init__.py
clfits/export.py
clfits/io.py
clfits/main.py
clfits/search.py
clfits-0.4.0.dist-info/licenses/LICENSE
clfits-0.4.0.dist-info/METADATA
clfits-0.4.0.dist-info/WHEEL
clfits-0.4.0.dist-info/entry_points.txt
clfits-0.4.0.dist-info/top_level.txt
clfits-0.4.0.dist-info/RECORD
