Metadata-Version: 2.4
Name: clfits
Version: 0.4.0
Summary: A command-line FITS header editor.
Author-email: Amber Malpas <malpas.1@osu.edu>
License: MIT License
Project-URL: Homepage, https://github.com/AmberLee2427/CLFits
Project-URL: Bug Tracker, https://github.com/AmberLee2427/CLFits/issues
Project-URL: Repository, https://github.com/AmberLee2427/CLFits.git
Classifier: Development Status :: 3 - Alpha
Classifier: Intended Audience :: Science/Research
Classifier: License :: OSI Approved :: MIT License
Classifier: Programming Language :: Python :: 3
Classifier: Programming Language :: Python :: 3.9
Classifier: Programming Language :: Python :: 3.10
Classifier: Programming Language :: Python :: 3.11
Classifier: Programming Language :: Python :: 3.12
Classifier: Operating System :: OS Independent
Classifier: Topic :: Scientific/Engineering :: Astronomy
Requires-Python: >=3.9
License-File: LICENSE
Requires-Dist: astropy
Requires-Dist: typer[all]
Requires-Dist: rich
Requires-Dist: pyyaml
Provides-Extra: dev
Requires-Dist: pytest; extra == "dev"
Requires-Dist: pytest-cov; extra == "dev"
Requires-Dist: pytest-doctestplus; extra == "dev"
Requires-Dist: ruff; extra == "dev"
Requires-Dist: mypy; extra == "dev"
Requires-Dist: bump-my-version; extra == "dev"
Requires-Dist: sphinx; extra == "dev"
Requires-Dist: furo; extra == "dev"
Requires-Dist: pre-commit; extra == "dev"
Requires-Dist: numpydoc; extra == "dev"
Provides-Extra: docs
Requires-Dist: sphinx; extra == "docs"
Requires-Dist: furo; extra == "docs"
Requires-Dist: numpydoc; extra == "docs"
Dynamic: license-file
